mypythontools_cicd/__init__.py
mypythontools_cicd/__main__.py
mypythontools_cicd/build_app/__init__.py
mypythontools_cicd/build_app/build_app_internal.py
mypythontools_cicd/cicd/__init__.py
mypythontools_cicd/cicd/cicd_internal.py
mypythontools_cicd/deploy/__init__.py
mypythontools_cicd/deploy/deploy_internal.py
mypythontools_cicd/docs/__init__.py
mypythontools_cicd/docs/docs_internal.py
mypythontools_cicd/git/__init__.py
mypythontools_cicd/git/git_internal.py
mypythontools_cicd/misc/__init__.py
mypythontools_cicd/misc/misc_internal.py
mypythontools_cicd/packages/__init__.py
mypythontools_cicd/packages/packages_internal.py
mypythontools_cicd/project_paths/__init__.py
mypythontools_cicd/project_paths/project_paths_internal.py
mypythontools_cicd/tests/__init__.py
mypythontools_cicd/tests/tests_internal.py
mypythontools_cicd/venvs/__init__.py
mypythontools_cicd/venvs/venvs_internal.py
mypythontools_cicd-0.0.35.dist-info/LICENSE
mypythontools_cicd-0.0.35.dist-info/METADATA
mypythontools_cicd-0.0.35.dist-info/WHEEL
mypythontools_cicd-0.0.35.dist-info/entry_points.txt
mypythontools_cicd-0.0.35.dist-info/top_level.txt
mypythontools_cicd-0.0.35.dist-info/RECORD
