Metadata-Version: 2.1
Name: mypythontools-cicd
Version: 0.0.35
Summary: Some tools/functions/snippets used across projects.
Home-page: https://github.com/Malachov/mypythontools_cicd
Author: Daniel Malachov
Author-email: malachovd@seznam.cz
License: mit
Keywords: CICD,documentation,tests,packages
Platform: any
Classifier: Development Status :: 3 - Alpha
Classifier: Environment :: Other Environment
Classifier: Intended Audience :: Developers
Classifier: Intended Audience :: Education
Classifier: License :: OSI Approved :: MIT License
Classifier: Natural Language :: English
Classifier: Operating System :: OS Independent
Classifier: Programming Language :: Python :: 3.7
Classifier: Programming Language :: Python :: 3.9
Classifier: Programming Language :: Python :: 3.10
Classifier: Programming Language :: Python :: 3.11
Classifier: Programming Language :: Python
Classifier: Topic :: Software Development :: Libraries :: Application Frameworks
Classifier: Topic :: Software Development :: Libraries :: Python Modules
Requires-Python: >=3.7
License-File: LICENSE
Requires-Dist: mypythontools (~=3.0.2)
Requires-Dist: mylogging (~=4.0.6)
Provides-Extra: all
Requires-Dist: mypythontools (~=3.0.2) ; extra == 'all'
Requires-Dist: mylogging (~=4.0.6) ; extra == 'all'
Requires-Dist: pyinstaller ; extra == 'all'
Requires-Dist: EelForkExcludeFiles ; extra == 'all'
Requires-Dist: build ; extra == 'all'
Requires-Dist: twine ; extra == 'all'
Requires-Dist: wheel ; extra == 'all'
Requires-Dist: sphinx ; extra == 'all'
Requires-Dist: GitPython ; extra == 'all'
Requires-Dist: black ; extra == 'all'
Requires-Dist: setuptools ; extra == 'all'
Requires-Dist: nbmake ; extra == 'all'
Requires-Dist: phmdoctest ; extra == 'all'
Requires-Dist: pytest ; extra == 'all'
Requires-Dist: pytest-cov ; extra == 'all'
Requires-Dist: pip-tools ; extra == 'all'
Requires-Dist: bandit ; extra == 'all'
Requires-Dist: line-profiler ; extra == 'all'
Requires-Dist: memory-profiler ; extra == 'all'
Requires-Dist: pydocstyle ; extra == 'all'
Requires-Dist: pylint ; extra == 'all'
Provides-Extra: build
Requires-Dist: pyinstaller ; extra == 'build'
Requires-Dist: EelForkExcludeFiles ; extra == 'build'
Provides-Extra: cicd
Requires-Dist: pyinstaller ; extra == 'cicd'
Requires-Dist: EelForkExcludeFiles ; extra == 'cicd'
Requires-Dist: build ; extra == 'cicd'
Requires-Dist: twine ; extra == 'cicd'
Requires-Dist: wheel ; extra == 'cicd'
Requires-Dist: sphinx ; extra == 'cicd'
Requires-Dist: GitPython ; extra == 'cicd'
Requires-Dist: black ; extra == 'cicd'
Requires-Dist: setuptools ; extra == 'cicd'
Requires-Dist: nbmake ; extra == 'cicd'
Requires-Dist: phmdoctest ; extra == 'cicd'
Requires-Dist: pytest ; extra == 'cicd'
Requires-Dist: pytest-cov ; extra == 'cicd'
Requires-Dist: pip-tools ; extra == 'cicd'
Provides-Extra: deploy
Requires-Dist: build ; extra == 'deploy'
Requires-Dist: twine ; extra == 'deploy'
Requires-Dist: wheel ; extra == 'deploy'
Provides-Extra: dev
Requires-Dist: bandit ; extra == 'dev'
Requires-Dist: black ; extra == 'dev'
Requires-Dist: line-profiler ; extra == 'dev'
Requires-Dist: memory-profiler ; extra == 'dev'
Requires-Dist: pydocstyle ; extra == 'dev'
Requires-Dist: pylint ; extra == 'dev'
Provides-Extra: docs
Requires-Dist: sphinx ; extra == 'docs'
Provides-Extra: git
Requires-Dist: GitPython ; extra == 'git'
Provides-Extra: misc
Requires-Dist: black ; extra == 'misc'
Provides-Extra: packages
Requires-Dist: setuptools ; extra == 'packages'
Provides-Extra: tests
Requires-Dist: nbmake ; extra == 'tests'
Requires-Dist: phmdoctest ; extra == 'tests'
Requires-Dist: pytest ; extra == 'tests'
Requires-Dist: pytest-cov ; extra == 'tests'
Requires-Dist: pip-tools ; extra == 'tests'
